pyccmetrics/__init__.py
pyccmetrics/metrics.py
pyccmetrics/metrics_utils.py
pyccmetrics/lib/build-languages.py
pyccmetrics/lib/my-languages.so
pyccmetrics-0.1.2.dist-info/LICENSE
pyccmetrics-0.1.2.dist-info/METADATA
pyccmetrics-0.1.2.dist-info/WHEEL
pyccmetrics-0.1.2.dist-info/top_level.txt
pyccmetrics-0.1.2.dist-info/RECORD
