Metadata-Version: 2.1
Name: pyccmetrics
Version: 0.1.2
Summary: Python package for calculating code complexity metrics of the target source code
Author-email: Mohammad Mahdi Mohajer <mmohajer9@hotmail.com>
Project-URL: Homepage, https://github.com/mmohajer9/pyccmetrics
Project-URL: Bug Tracker, https://github.com/mmohajer9/pyccmetrics/issues
Classifier: Programming Language :: Python :: 3
Classifier: License :: OSI Approved :: MIT License
Classifier: Operating System :: OS Independent
Requires-Python: >=3.6
License-File: LICENSE
Requires-Dist: tree-sitter (>=0.20.1)
